wandb_core/__init__.py
wandb_core-0.17.0b11.dist-info/METADATA
wandb_core-0.17.0b11.dist-info/WHEEL
wandb_core-0.17.0b11.dist-info/top_level.txt
wandb_core-0.17.0b11.dist-info/RECORD
