Metadata-Version: 2.1
Name: wandb-core
Version: 0.17.0b11
Summary: W&B Core Library
License: MIT License
Requires-Python: >=3.7
